testing/main.py
testing/print_dirs.py
zmc/__init__.py
zmc/version.py
zmc/components/__init__.py
zmc/components/button_component.py
zmc/components/button_component_test.py
zmc/components/conftest.py
zmc/components/display_components.py
zmc/components/graph_components.py
zmc/components/single_boolean_components.py
zmc/components/single_boolean_components_test.py
zmc/components/single_number_components.py
zmc/components/single_number_components_test.py
zmc/components/single_text_components.py
zmc/components/single_text_components_test.py
zmc/components/core/__init__.py
zmc/components/core/base_component.py
zmc/components/core/base_component_test.py
zmc/components/core/data_sender_base_component.py
zmc/components/core/data_sender_base_component_test.py
zmc/components/core/single_value_component.py
zmc/components/core/single_value_component_test.py
zmc/components/core/value_receiver_base_component.py
zmc/components/core/value_receiver_base_component_test.py
zmc/connect/__init__.py
zmc/connect/async_utils.py
zmc/connect/async_utils_test.py
zmc/connect/connector.py
zmc/connect/connector_config.py
zmc/connect/connector_context.py
zmc/connect/connector_test.py
zmc/connect/mock_connector.py
zmc/connect/websocket_client.py
zmc/connect/websocket_server.py
zmc/utils/__init__.py
zmc/utils/callback.py
zmc/utils/callback_test.py
zmc/utils/instance_registry.py
zmc/utils/instance_registry_test.py
zmc/utils/logger.py
zmc/utils/singleton.py
zmc/utils/singleton_test.py
zmc/utils/deprecated/__init__.py
zmc/utils/deprecated/deprecated.py
zmc/utils/deprecated/deprecated_test.py
zmc-0.1.2b2.dist-info/METADATA
zmc-0.1.2b2.dist-info/WHEEL
zmc-0.1.2b2.dist-info/top_level.txt
zmc-0.1.2b2.dist-info/RECORD
